{
	"TOKEN_OUTFIT_HERO_JABY_SUIT": {
		"Guid": "ddce36eb-2c88-492c-bfe1-02735b8efb7e",
		"Type": "disguise",
		"Subtype": "casual",
		"ImageId": "",
		"RMTPrice": -1,
		"GamePrice": -1,
		"IsPurchasable": false,
		"IsPublished": true,
		"IsDroppable": false,
		"Capabilities": [],
		"Qualities": {},
		"Properties": {
			"Quality": 4,
			"Rarity": "common",
			"LoadoutSlot": "disguise",
			"IsConsumable": false,
			"RepositoryId": "b865c2f1-7ae4-4593-a709-b459757660c5",
			"OrderIndex": 21
		},
		"Rarity": "common"
	}
}
