{
	"TOKEN_OUTFIT_HERO_CONOR_DRESS": {
		"Guid": "edcdafb7-74ce-4163-80ed-013a0b8bc892",
		"Type": "disguise",
		"Subtype": "casual",
		"ImageId": "",
		"RMTPrice": -1,
		"GamePrice": -1,
		"IsPurchasable": false,
		"IsPublished": true,
		"IsDroppable": false,
		"Capabilities": [],
		"Qualities": {},
		"Properties": {
			"Quality": 4,
			"Rarity": "common",
			"LoadoutSlot": "disguise",
			"IsConsumable": false,
			"RepositoryId": "360fb613-dbfd-4eca-8f22-e78aa950282a",
			"OrderIndex": 21
		},
		"Rarity": "common"
	}
}
